bitshuffle/h5.cpython-310-x86_64-linux-gnu.so
bitshuffle/__init__.py
bitshuffle/ext.cpython-310-x86_64-linux-gnu.so
bitshuffle/plugin/libh5bshuf.cpython-310-x86_64-linux-gnu.so
bitshuffle/plugin/libh5LZF.cpython-310-x86_64-linux-gnu.so
bitshuffle-0.5.2.dist-info/LICENSE
bitshuffle-0.5.2.dist-info/METADATA
bitshuffle-0.5.2.dist-info/RECORD
bitshuffle-0.5.2.dist-info/WHEEL
bitshuffle-0.5.2.dist-info/top_level.txt
bitshuffle.libs/libgomp-a34b3233.so.1.0.0
bitshuffle.libs/libhdf5-42e6a05d.so.310.4.0
