Metadata-Version: 2.1
Name: bitshuffle
Version: 0.5.2
Summary: Bitshuffle filter for improving typed data compression.
Home-page: https://github.com/kiyo-masui/bitshuffle
Download-URL: https://github.com/kiyo-masui/bitshuffle/tarball/0.5.2
Author: Kiyoshi Wesley Masui
Author-email: kiyo@physics.ubc.ca
License: MIT
Keywords: compression,hdf5,numpy
Requires-Python: >=3.9
License-File: LICENSE
Requires-Dist: setuptools>=0.7
Requires-Dist: Cython>=0.19
Requires-Dist: numpy>=1.24
Requires-Dist: h5py>=2.4.0
